[
  {
    "automation_id": "auto_discover",
    "enabled": true,
    "schedule_cron": "0 9 */1 * *",
    "days_interval": 1,
    "times": [
      "09:00"
    ],
    "last_run_at": "2026-05-31T12:08:06.265Z",
    "updated_at": "2026-05-31T12:08:06.267Z"
  },
  {
    "automation_id": "auto_content",
    "enabled": true,
    "schedule_cron": "0 2 */1 * *",
    "days_interval": 1,
    "times": [
      "02:00"
    ],
    "last_run_at": null,
    "updated_at": "2026-05-31T12:07:53.885Z"
  },
  {
    "automation_id": "auto_prices",
    "enabled": true,
    "schedule_cron": "0 9 */2 * *;0 19 */2 * *",
    "days_interval": 2,
    "times": [
      "09:00",
      "19:00"
    ],
    "last_run_at": null,
    "updated_at": "2026-05-31T11:32:29.662Z"
  }
]
